<?xml version="1.0" encoding="utf-8"?>
<odoo>

<record id="unece_code_list_form" model="ir.ui.view">
    <field name="name">unece.code.list.form</field>
    <field name="model">unece.code.list</field>
    <field name="inherit_id" ref="base_unece.unece_code_list_form"/>
    <field name="arch" type="xml">
        <field name="type" position="after">
            <field name="scheme_id">Scheme ID</field>
        </field>
    </field>
</record>

<record id="unece_code_list_tree" model="ir.ui.view">
    <field name="name">unece.code.list.tree</field>
    <field name="model">unece.code.list</field>
    <field name="inherit_id" ref="base_unece.unece_code_list_tree"/>
    <field name="arch" type="xml">
        <field name="type" position="after">
            <field name="scheme_id">Scheme ID</field>
        </field>
    </field>
</record>

</odoo>
